work_os_ipython_magic/__init__.py
work_os_ipython_magic/team_parser.py
work_os_ipython_magic/work_os_magic.py
work_os_ipython_magic-0.0.5.dist-info/LICENSE
work_os_ipython_magic-0.0.5.dist-info/METADATA
work_os_ipython_magic-0.0.5.dist-info/WHEEL
work_os_ipython_magic-0.0.5.dist-info/top_level.txt
work_os_ipython_magic-0.0.5.dist-info/RECORD
