Metadata-Version: 2.1
Name: work-os-ipython-magic
Version: 0.0.5
Summary: Work OS IPython Custom Magic
Home-page: https://github.com/dyzfromyt/work_os_ipython_magic
Author: dyzfromyt
Author-email: dyzfromyt@gmail.com
License: UNKNOWN
Project-URL: Bug Tracker, https://github.com/dyzfromyt/work_os_ipython_magic/issues
Platform: UNKNOWN
Classifier: Development Status :: 2 - Pre-Alpha
Classifier: Framework :: IPython
Classifier: Framework :: Jupyter
Classifier: Programming Language :: Python :: 3
Classifier: License :: OSI Approved :: Apache Software License
Classifier: Operating System :: OS Independent
Requires-Python: >=3.6
License-File: LICENSE
Requires-Dist: pyyaml
